{
    "version": "3.0",
    "status": "Jherez Taylor successfully connected with the Hatebase API on October 7, 2016, at 2:04 PM. Filters: about_nationality=1|language=eng|page=1",
    "page": "1",
    "number_of_results": "146",
    "number_of_results_on_this_page": "100",
    "warnings": {
        "0": "\n  "
    },
    "errors": {
        "0": "\n  "
    },
    "number_of_queries_today": "15",
    "data": {
        "datapoint": [{
            "vocabulary": "ABC",
            "variant_of": {},
            "pronunciation": {},
            "meaning": "[1] American-born Chinese [2] Australian-born Chinese",
            "language": "eng",
            "about_ethnicity": "1",
            "about_nationality": "1",
            "about_religion": "0",
            "about_gender": "0",
            "about_sexual_orientation": "0",
            "about_disability": "0",
            "about_class": "0",
            "archaic": "0",
            "offensiveness": "0.00",
            "number_of_revisions": "1",
            "number_of_variants": "0",
            "variants": {},
            "number_of_sightings": "0",
            "last_sighting": {},
            "number_of_citations": "1"
        }, {
            "vocabulary": "Argie",
            "variant_of": {},
            "pronunciation": {},
            "meaning": "An Argentinian.",
            "language": "eng",
            "about_ethnicity": "0",
            "about_nationality": "1",
            "about_religion": "0",
            "about_gender": "0",
            "about_sexual_orientation": "0",
            "about_disability": "0",
            "about_class": "0",
            "archaic": "0",
            "offensiveness": "0.03",
            "number_of_revisions": "1",
            "number_of_variants": "0",
            "variants": {},
            "number_of_sightings": "455",
            "last_sighting": "2016-10-04 03:18:06",
            "number_of_citations": "1"
        }, {
            "vocabulary": "bamboo coon",
            "variant_of": {},
            "pronunciation": {},
            "meaning": "A person of Chinese ancestry",
            "language": "eng",
            "about_ethnicity": "1",
            "about_nationality": "1",
            "about_religion": "0",
            "about_gender": "0",
            "about_sexual_orientation": "0",
            "about_disability": "0",
            "about_class": "0",
            "archaic": "0",
            "offensiveness": "0.93",
            "number_of_revisions": "1",
            "number_of_variants": "0",
            "variants": {},
            "number_of_sightings": "3",
            "last_sighting": "2016-06-03 22:59:04",
            "number_of_citations": "0"
        }, {
            "vocabulary": "banana bender",
            "variant_of": {},
            "pronunciation": {},
            "meaning": "An Australian from Queensland",
            "language": "eng",
            "about_ethnicity": "0",
            "about_nationality": "1",
            "about_religion": "0",
            "about_gender": "0",
            "about_sexual_orientation": "0",
            "about_disability": "0",
            "about_class": "0",
            "archaic": "0",
            "offensiveness": "0.10",
            "number_of_revisions": "1",
            "number_of_variants": "1",
            "variants": "banana lander",
            "number_of_sightings": "159",
            "last_sighting": "2016-09-30 21:22:36",
            "number_of_citations": "0"
        }, {
            "vocabulary": "banana lander",
            "variant_of": "banana bender",
            "pronunciation": {},
            "meaning": "An Australian from Queensland",
            "language": "eng",
            "about_ethnicity": "0",
            "about_nationality": "1",
            "about_religion": "0",
            "about_gender": "0",
            "about_sexual_orientation": "0",
            "about_disability": "0",
            "about_class": "0",
            "archaic": "0",
            "offensiveness": "0.00",
            "number_of_revisions": "1",
            "number_of_variants": "0",
            "variants": {},
            "number_of_sightings": "0",
            "last_sighting": {},
            "number_of_citations": "0"
        }, {
            "vocabulary": "bans and cans",
            "variant_of": {},
            "pronunciation": {},
            "meaning": "Mexicans, Puerto Ricans and Cubans.",
            "language": "eng",
            "about_ethnicity": "1",
            "about_nationality": "1",
            "about_religion": "0",
            "about_gender": "0",
            "about_sexual_orientation": "0",
            "about_disability": "0",
            "about_class": "0",
            "archaic": "0",
            "offensiveness": "0.13",
            "number_of_revisions": "0",
            "number_of_variants": "0",
            "variants": {},
            "number_of_sightings": "0",
            "last_sighting": {},
            "number_of_citations": "0"
        }, {
            "vocabulary": "beaner shnitzel",
            "variant_of": {},
            "pronunciation": {},
            "meaning": "Offspring of a hispanic parent and a German parent",
            "language": "eng",
            "about_ethnicity": "1",
            "about_nationality": "1",
            "about_religion": "0",
            "about_gender": "0",
            "about_sexual_orientation": "0",
            "about_disability": "0",
            "about_class": "0",
            "archaic": "0",
            "offensiveness": "0.00",
            "number_of_revisions": "1",
            "number_of_variants": "0",
            "variants": {},
            "number_of_sightings": "0",
            "last_sighting": {},
            "number_of_citations": "0"
        }, {
            "vocabulary": "Bengali",
            "variant_of": {},
            "pronunciation": {},
            "meaning": "This is not hate speech when applied to a Bengali citizen or inhabitant of Bangladesh, but is used by Myanmar Buddhists to foment hate and exclusion from citizenship of Muslims. Calling them \"Bengali\" indicates they should be eliminated from Myanmar.",
            "language": "eng",
            "about_ethnicity": "1",
            "about_nationality": "1",
            "about_religion": "1",
            "about_gender": "0",
            "about_sexual_orientation": "0",
            "about_disability": "0",
            "about_class": "0",
            "archaic": "0",
            "offensiveness": "0.00",
            "number_of_revisions": "2",
            "number_of_variants": "0",
            "variants": {},
            "number_of_sightings": "0",
            "last_sighting": {},
            "number_of_citations": "1"
        }, {
            "vocabulary": "bhrempti",
            "variant_of": {},
            "pronunciation": {},
            "meaning": "An Indian, based on the perceived pronunciation of 'twenty'.",
            "language": "eng",
            "about_ethnicity": "1",
            "about_nationality": "1",
            "about_religion": "0",
            "about_gender": "0",
            "about_sexual_orientation": "0",
            "about_disability": "0",
            "about_class": "0",
            "archaic": "0",
            "offensiveness": "0.00",
            "number_of_revisions": "0",
            "number_of_variants": "0",
            "variants": {},
            "number_of_sightings": "0",
            "last_sighting": {},
            "number_of_citations": "0"
        }, {
            "vocabulary": "black dago",
            "variant_of": {},
            "pronunciation": {},
            "meaning": "[1] A Sicilian [2] A darker-skinned Italian [3] An Italian of allegedly African ancestry",
            "language": "eng",
            "about_ethnicity": "1",
            "about_nationality": "1",
            "about_religion": "0",
            "about_gender": "0",
            "about_sexual_orientation": "0",
            "about_disability": "0",
            "about_class": "0",
            "archaic": "0",
            "offensiveness": "1.00",
            "number_of_revisions": "1",
            "number_of_variants": "0",
            "variants": {},
            "number_of_sightings": "0",
            "last_sighting": {},
            "number_of_citations": "2"
        }, {
            "vocabulary": "blaxican",
            "variant_of": {},
            "pronunciation": {},
            "meaning": "A person of mixed Mexican and African ancestry",
            "language": "eng",
            "about_ethnicity": "1",
            "about_nationality": "1",
            "about_religion": "0",
            "about_gender": "0",
            "about_sexual_orientation": "0",
            "about_disability": "0",
            "about_class": "0",
            "archaic": "0",
            "offensiveness": "0.00",
            "number_of_revisions": "1",
            "number_of_variants": "0",
            "variants": {},
            "number_of_sightings": "108",
            "last_sighting": "2016-09-15 23:15:57",
            "number_of_citations": "0"
        }, {
            "vocabulary": "blockhead",
            "variant_of": {},
            "pronunciation": {},
            "meaning": "In Australia, a person of Macedonian descent.",
            "language": "eng",
            "about_ethnicity": "0",
            "about_nationality": "1",
            "about_religion": "0",
            "about_gender": "0",
            "about_sexual_orientation": "0",
            "about_disability": "0",
            "about_class": "0",
            "archaic": "0",
            "offensiveness": "0.00",
            "number_of_revisions": "0",
            "number_of_variants": "0",
            "variants": {},
            "number_of_sightings": "0",
            "last_sighting": {},
            "number_of_citations": "0"
        }, {
            "vocabulary": "bog hopper",
            "variant_of": "Bog Irish",
            "pronunciation": {},
            "meaning": "A person of common or low class Irish ancestry.",
            "language": "eng",
            "about_ethnicity": "0",
            "about_nationality": "1",
            "about_religion": "0",
            "about_gender": "0",
            "about_sexual_orientation": "0",
            "about_disability": "0",
            "about_class": "1",
            "archaic": "0",
            "offensiveness": "0.00",
            "number_of_revisions": "1",
            "number_of_variants": "0",
            "variants": {},
            "number_of_sightings": "10",
            "last_sighting": "2015-12-30 16:45:12",
            "number_of_citations": "0"
        }, {
            "vocabulary": "Bog Irish",
            "variant_of": {},
            "pronunciation": {},
            "meaning": "A person of common or low class Irish ancestry.",
            "language": "eng",
            "about_ethnicity": "0",
            "about_nationality": "1",
            "about_religion": "0",
            "about_gender": "0",
            "about_sexual_orientation": "0",
            "about_disability": "0",
            "about_class": "1",
            "archaic": "0",
            "offensiveness": "0.00",
            "number_of_revisions": "0",
            "number_of_variants": "3",
            "variants": "bog hopper; bog jumper; bog trotter",
            "number_of_sightings": "79",
            "last_sighting": "2016-10-01 05:25:11",
            "number_of_citations": "0"
        }, {
            "vocabulary": "bog jumper",
            "variant_of": "Bog Irish",
            "pronunciation": {},
            "meaning": "A person of common or low class Irish ancestry.",
            "language": "eng",
            "about_ethnicity": "0",
            "about_nationality": "1",
            "about_religion": "0",
            "about_gender": "0",
            "about_sexual_orientation": "0",
            "about_disability": "0",
            "about_class": "1",
            "archaic": "0",
            "offensiveness": "0.00",
            "number_of_revisions": "1",
            "number_of_variants": "0",
            "variants": {},
            "number_of_sightings": "3",
            "last_sighting": "2015-08-14 14:51:03",
            "number_of_citations": "0"
        }, {
            "vocabulary": "bog trotter",
            "variant_of": "Bog Irish",
            "pronunciation": {},
            "meaning": "A person of common or low class Irish ancestry.",
            "language": "eng",
            "about_ethnicity": "0",
            "about_nationality": "1",
            "about_religion": "0",
            "about_gender": "0",
            "about_sexual_orientation": "0",
            "about_disability": "0",
            "about_class": "1",
            "archaic": "0",
            "offensiveness": "0.00",
            "number_of_revisions": "0",
            "number_of_variants": "0",
            "variants": {},
            "number_of_sightings": "181",
            "last_sighting": "2016-10-01 17:33:39",
            "number_of_citations": "0"
        }, {
            "vocabulary": "bogan",
            "variant_of": {},
            "pronunciation": {},
            "meaning": "[1] A male Native American. [2] In Australia or New Zealand, white trash or a redneck.",
            "language": "eng",
            "about_ethnicity": "1",
            "about_nationality": "1",
            "about_religion": "0",
            "about_gender": "0",
            "about_sexual_orientation": "0",
            "about_disability": "0",
            "about_class": "1",
            "archaic": "0",
            "offensiveness": "0.10",
            "number_of_revisions": "1",
            "number_of_variants": "0",
            "variants": {},
            "number_of_sightings": "2311",
            "last_sighting": "2016-10-04 08:56:03",
            "number_of_citations": "1"
        }, {
            "vocabulary": "book book",
            "variant_of": {},
            "pronunciation": {},
            "meaning": "In Hawaii, denotes a Filipino, from the alleged sound of Filipino language.",
            "language": "eng",
            "about_ethnicity": "1",
            "about_nationality": "1",
            "about_religion": "0",
            "about_gender": "0",
            "about_sexual_orientation": "0",
            "about_disability": "0",
            "about_class": "0",
            "archaic": "0",
            "offensiveness": "0.00",
            "number_of_revisions": "0",
            "number_of_variants": "1",
            "variants": "buk buk",
            "number_of_sightings": "0",
            "last_sighting": {},
            "number_of_citations": "0"
        }, {
            "vocabulary": "boon",
            "variant_of": "booner",
            "pronunciation": {},
            "meaning": "Canberra word for white trash or redneck, sometimes shortened to boon",
            "language": "eng",
            "about_ethnicity": "0",
            "about_nationality": "1",
            "about_religion": "0",
            "about_gender": "0",
            "about_sexual_orientation": "0",
            "about_disability": "0",
            "about_class": "1",
            "archaic": "0",
            "offensiveness": "0.00",
            "number_of_revisions": "1",
            "number_of_variants": "0",
            "variants": {},
            "number_of_sightings": "0",
            "last_sighting": {},
            "number_of_citations": "0"
        }, {
            "vocabulary": "booner",
            "variant_of": {},
            "pronunciation": {},
            "meaning": "Canberra word for white trash or redneck, sometimes shortened to boon",
            "language": "eng",
            "about_ethnicity": "0",
            "about_nationality": "1",
            "about_religion": "0",
            "about_gender": "0",
            "about_sexual_orientation": "0",
            "about_disability": "0",
            "about_class": "1",
            "archaic": "0",
            "offensiveness": "0.00",
            "number_of_revisions": "1",
            "number_of_variants": "1",
            "variants": "boon",
            "number_of_sightings": "189",
            "last_sighting": "2016-09-29 05:51:37",
            "number_of_citations": "1"
        }, {
            "vocabulary": "boxhead",
            "variant_of": {},
            "pronunciation": {},
            "meaning": "A person of German descent.",
            "language": "eng",
            "about_ethnicity": "0",
            "about_nationality": "1",
            "about_religion": "0",
            "about_gender": "0",
            "about_sexual_orientation": "0",
            "about_disability": "0",
            "about_class": "0",
            "archaic": "0",
            "offensiveness": "0.89",
            "number_of_revisions": "0",
            "number_of_variants": "0",
            "variants": {},
            "number_of_sightings": "0",
            "last_sighting": {},
            "number_of_citations": "0"
        }, {
            "vocabulary": "bubble",
            "variant_of": {},
            "pronunciation": {},
            "meaning": "A person of Greek descent. 'Bubble and squeak' is Cockney slang for Greek.",
            "language": "eng",
            "about_ethnicity": "1",
            "about_nationality": "1",
            "about_religion": "0",
            "about_gender": "0",
            "about_sexual_orientation": "0",
            "about_disability": "0",
            "about_class": "0",
            "archaic": "0",
            "offensiveness": "0.00",
            "number_of_revisions": "0",
            "number_of_variants": "0",
            "variants": {},
            "number_of_sightings": "0",
            "last_sighting": {},
            "number_of_citations": "0"
        }, {
            "vocabulary": "buckethead",
            "variant_of": {},
            "pronunciation": {},
            "meaning": "A person of Korean descent.",
            "language": "eng",
            "about_ethnicity": "1",
            "about_nationality": "1",
            "about_religion": "0",
            "about_gender": "0",
            "about_sexual_orientation": "0",
            "about_disability": "0",
            "about_class": "0",
            "archaic": "0",
            "offensiveness": "0.00",
            "number_of_revisions": "0",
            "number_of_variants": "0",
            "variants": {},
            "number_of_sightings": "1",
            "last_sighting": "2013-04-08 00:00:00",
            "number_of_citations": "0"
        }, {
            "vocabulary": "buk buk",
            "variant_of": "book book",
            "pronunciation": {},
            "meaning": "In Hawaii, denotes a Filipino, from the alleged sound of Filipino language.",
            "language": "eng",
            "about_ethnicity": "1",
            "about_nationality": "1",
            "about_religion": "0",
            "about_gender": "0",
            "about_sexual_orientation": "0",
            "about_disability": "0",
            "about_class": "0",
            "archaic": "0",
            "offensiveness": "0.00",
            "number_of_revisions": "1",
            "number_of_variants": "0",
            "variants": {},
            "number_of_sightings": "2",
            "last_sighting": "2016-09-08 15:04:24",
            "number_of_citations": "0"
        }, {
            "vocabulary": "butterhead",
            "variant_of": {},
            "pronunciation": {},
            "meaning": "[1] A person of African descent. [2] WWII slur for a Japanese person.",
            "language": "eng",
            "about_ethnicity": "1",
            "about_nationality": "1",
            "about_religion": "0",
            "about_gender": "0",
            "about_sexual_orientation": "0",
            "about_disability": "0",
            "about_class": "0",
            "archaic": "0",
            "offensiveness": "0.00",
            "number_of_revisions": "1",
            "number_of_variants": "0",
            "variants": {},
            "number_of_sightings": "0",
            "last_sighting": {},
            "number_of_citations": "0"
        }, {
            "vocabulary": "camel fucker",
            "variant_of": {},
            "pronunciation": {},
            "meaning": "[1] An Arab. [2] A Muslim.",
            "language": "eng",
            "about_ethnicity": "1",
            "about_nationality": "1",
            "about_religion": "1",
            "about_gender": "0",
            "about_sexual_orientation": "0",
            "about_disability": "0",
            "about_class": "0",
            "archaic": "0",
            "offensiveness": "0.74",
            "number_of_revisions": "1",
            "number_of_variants": "0",
            "variants": {},
            "number_of_sightings": "832",
            "last_sighting": "2016-10-04 14:33:39",
            "number_of_citations": "0"
        }, {
            "vocabulary": "celestial",
            "variant_of": {},
            "pronunciation": {},
            "meaning": "In the late 1900s, Chinese people in Australia were often referred to as 'Celestials', a reference to their coming from the 'Celestial Empire' (i.e. China)",
            "language": "eng",
            "about_ethnicity": "1",
            "about_nationality": "1",
            "about_religion": "0",
            "about_gender": "0",
            "about_sexual_orientation": "0",
            "about_disability": "0",
            "about_class": "0",
            "archaic": "1",
            "offensiveness": "0.00",
            "number_of_revisions": "0",
            "number_of_variants": "0",
            "variants": {},
            "number_of_sightings": "0",
            "last_sighting": {},
            "number_of_citations": "0"
        }, {
            "vocabulary": "Charlie",
            "variant_of": {},
            "pronunciation": {},
            "meaning": "[1] To African-Americans of the 1960s-1970s, white people as a reified collective oppressor group, similar to The Man or The System. [2] Non-pejorative slang term used by American troops as a shorthand term for Vietnamese guerrillas. Derived from the verbal shorthand for 'Victor Charlie', the NATO phonetic alphabet for VC, the abbreviation for Viet Cong. Other references to the Viet Cong included 'Mr. Charles' as a rueful admission of the skill at asymmetric warfare.",
            "language": "eng",
            "about_ethnicity": "1",
            "about_nationality": "1",
            "about_religion": "0",
            "about_gender": "0",
            "about_sexual_orientation": "0",
            "about_disability": "0",
            "about_class": "0",
            "archaic": "1",
            "offensiveness": "0.00",
            "number_of_revisions": "0",
            "number_of_variants": "0",
            "variants": {},
            "number_of_sightings": "0",
            "last_sighting": {},
            "number_of_citations": "0"
        }, {
            "vocabulary": "cheese eating surrender monkey",
            "variant_of": {},
            "pronunciation": {},
            "meaning": "A French person, from the defeat of the French against the German in 1940, and the huge variety of cheeses originating from France. Gained popularity after the term was used on an episode of The Simpsons and was subsequently adopted by right-wing pundits. Rarely used today.",
            "language": "eng",
            "about_ethnicity": "0",
            "about_nationality": "1",
            "about_religion": "0",
            "about_gender": "0",
            "about_sexual_orientation": "0",
            "about_disability": "0",
            "about_class": "0",
            "archaic": "1",
            "offensiveness": "0.00",
            "number_of_revisions": "1",
            "number_of_variants": "1",
            "variants": "surrender monkey",
            "number_of_sightings": "0",
            "last_sighting": {},
            "number_of_citations": "1"
        }, {
            "vocabulary": "chigger",
            "variant_of": {},
            "pronunciation": {},
            "meaning": "[1] A Chinese person trying to act like a black person. [2] A person of mixed black and Asian parentage.",
            "language": "eng",
            "about_ethnicity": "1",
            "about_nationality": "1",
            "about_religion": "0",
            "about_gender": "0",
            "about_sexual_orientation": "0",
            "about_disability": "0",
            "about_class": "0",
            "archaic": "0",
            "offensiveness": "0.00",
            "number_of_revisions": "0",
            "number_of_variants": "0",
            "variants": {},
            "number_of_sightings": "0",
            "last_sighting": {},
            "number_of_citations": "0"
        }, {
            "vocabulary": "Chinaman",
            "variant_of": {},
            "pronunciation": {},
            "meaning": "Found offensive, although it is a translation of the Chinese. It was used in the gold rush and railway-construction eras in western North America, when discrimination against Chinese was common.",
            "language": "eng",
            "about_ethnicity": "0",
            "about_nationality": "1",
            "about_religion": "0",
            "about_gender": "0",
            "about_sexual_orientation": "0",
            "about_disability": "0",
            "about_class": "0",
            "archaic": "1",
            "offensiveness": "0.40",
            "number_of_revisions": "0",
            "number_of_variants": "0",
            "variants": {},
            "number_of_sightings": "2450",
            "last_sighting": "2016-10-04 16:59:18",
            "number_of_citations": "0"
        }, {
            "vocabulary": "Chinese wetback",
            "variant_of": {},
            "pronunciation": {},
            "meaning": "A Filipino, particularly having a Mexican and Chinese heritage.",
            "language": "eng",
            "about_ethnicity": "1",
            "about_nationality": "1",
            "about_religion": "0",
            "about_gender": "0",
            "about_sexual_orientation": "0",
            "about_disability": "0",
            "about_class": "0",
            "archaic": "0",
            "offensiveness": "0.00",
            "number_of_revisions": "0",
            "number_of_variants": "0",
            "variants": {},
            "number_of_sightings": "1",
            "last_sighting": "2013-10-22 19:35:56",
            "number_of_citations": "0"
        }, {
            "vocabulary": "chinig",
            "variant_of": {},
            "pronunciation": {},
            "meaning": "A person of mixed black and Chinese parentage.",
            "language": "eng",
            "about_ethnicity": "1",
            "about_nationality": "1",
            "about_religion": "0",
            "about_gender": "0",
            "about_sexual_orientation": "0",
            "about_disability": "0",
            "about_class": "0",
            "archaic": "0",
            "offensiveness": "0.00",
            "number_of_revisions": "0",
            "number_of_variants": "0",
            "variants": {},
            "number_of_sightings": "1",
            "last_sighting": "2016-03-08 04:52:26",
            "number_of_citations": "0"
        }, {
            "vocabulary": "chink",
            "variant_of": {},
            "pronunciation": {},
            "meaning": "A person of Chinese descent. Considered extremely derogatory, exemplified by a US school that had to stop using the term as a sports mascot in 1980.",
            "language": "eng",
            "about_ethnicity": "0",
            "about_nationality": "1",
            "about_religion": "0",
            "about_gender": "0",
            "about_sexual_orientation": "0",
            "about_disability": "0",
            "about_class": "0",
            "archaic": "0",
            "offensiveness": "0.66",
            "number_of_revisions": "0",
            "number_of_variants": "0",
            "variants": {},
            "number_of_sightings": "295",
            "last_sighting": "2016-10-04 19:20:48",
            "number_of_citations": "0"
        }, {
            "vocabulary": "chink a billy",
            "variant_of": {},
            "pronunciation": {},
            "meaning": "A rural person of Chinese descent.",
            "language": "eng",
            "about_ethnicity": "1",
            "about_nationality": "1",
            "about_religion": "0",
            "about_gender": "0",
            "about_sexual_orientation": "0",
            "about_disability": "0",
            "about_class": "1",
            "archaic": "0",
            "offensiveness": "0.00",
            "number_of_revisions": "0",
            "number_of_variants": "0",
            "variants": {},
            "number_of_sightings": "0",
            "last_sighting": {},
            "number_of_citations": "0"
        }, {
            "vocabulary": "chonky",
            "variant_of": {},
            "pronunciation": {},
            "meaning": "A person of Asian descent with perceived Caucasian mannerisms. Concatenation of Chinese and honky.",
            "language": "eng",
            "about_ethnicity": "1",
            "about_nationality": "1",
            "about_religion": "0",
            "about_gender": "0",
            "about_sexual_orientation": "0",
            "about_disability": "0",
            "about_class": "0",
            "archaic": "0",
            "offensiveness": "0.00",
            "number_of_revisions": "0",
            "number_of_variants": "1",
            "variants": "chunky",
            "number_of_sightings": "289",
            "last_sighting": "2016-09-29 13:42:01",
            "number_of_citations": "0"
        }, {
            "vocabulary": "chunky",
            "variant_of": "chonky",
            "pronunciation": {},
            "meaning": "A person of Asian descent with perceived Caucasian mannerisms. Concatenation of Chinese and honky.",
            "language": "eng",
            "about_ethnicity": "1",
            "about_nationality": "1",
            "about_religion": "0",
            "about_gender": "0",
            "about_sexual_orientation": "0",
            "about_disability": "0",
            "about_class": "0",
            "archaic": "0",
            "offensiveness": "0.00",
            "number_of_revisions": "0",
            "number_of_variants": "0",
            "variants": {},
            "number_of_sightings": "0",
            "last_sighting": {},
            "number_of_citations": "0"
        }, {
            "vocabulary": "cow kisser",
            "variant_of": {},
            "pronunciation": {},
            "meaning": "A person of Indian descent, from the worship of cows.",
            "language": "eng",
            "about_ethnicity": "1",
            "about_nationality": "1",
            "about_religion": "0",
            "about_gender": "0",
            "about_sexual_orientation": "0",
            "about_disability": "0",
            "about_class": "0",
            "archaic": "0",
            "offensiveness": "0.00",
            "number_of_revisions": "0",
            "number_of_variants": "0",
            "variants": {},
            "number_of_sightings": "6",
            "last_sighting": "2016-09-04 20:24:28",
            "number_of_citations": "0"
        }, {
            "vocabulary": "dingo fucker",
            "variant_of": {},
            "pronunciation": {},
            "meaning": "An Australian",
            "language": "eng",
            "about_ethnicity": "0",
            "about_nationality": "1",
            "about_religion": "0",
            "about_gender": "0",
            "about_sexual_orientation": "0",
            "about_disability": "0",
            "about_class": "0",
            "archaic": "0",
            "offensiveness": "0.00",
            "number_of_revisions": "1",
            "number_of_variants": "0",
            "variants": {},
            "number_of_sightings": "70",
            "last_sighting": "2016-09-19 18:22:37",
            "number_of_citations": "0"
        }, {
            "vocabulary": "dink",
            "variant_of": {},
            "pronunciation": {},
            "meaning": "[1] An Asian. [2] A Vietnamese person. [3] A North Vietnamese soldier or guerrilla in the Vietnam War.",
            "language": "eng",
            "about_ethnicity": "1",
            "about_nationality": "1",
            "about_religion": "0",
            "about_gender": "0",
            "about_sexual_orientation": "0",
            "about_disability": "0",
            "about_class": "0",
            "archaic": "1",
            "offensiveness": "0.00",
            "number_of_revisions": "0",
            "number_of_variants": "0",
            "variants": {},
            "number_of_sightings": "0",
            "last_sighting": {},
            "number_of_citations": "0"
        }, {
            "vocabulary": "dogan",
            "variant_of": {},
            "pronunciation": {},
            "meaning": "In Canada, an Irish Catholic [19th century on; origin uncertain: perhaps from Dugan, an Irish surname].",
            "language": "eng",
            "about_ethnicity": "0",
            "about_nationality": "1",
            "about_religion": "1",
            "about_gender": "0",
            "about_sexual_orientation": "0",
            "about_disability": "0",
            "about_class": "0",
            "archaic": "0",
            "offensiveness": "0.00",
            "number_of_revisions": "0",
            "number_of_variants": "1",
            "variants": "dogun",
            "number_of_sightings": "0",
            "last_sighting": {},
            "number_of_citations": "0"
        }, {
            "vocabulary": "dogun",
            "variant_of": "dogan",
            "pronunciation": {},
            "meaning": "In Canada, an Irish Catholic [19th century on; origin uncertain: perhaps from Dugan, an Irish surname].",
            "language": "eng",
            "about_ethnicity": "0",
            "about_nationality": "1",
            "about_religion": "1",
            "about_gender": "0",
            "about_sexual_orientation": "0",
            "about_disability": "0",
            "about_class": "0",
            "archaic": "0",
            "offensiveness": "0.00",
            "number_of_revisions": "0",
            "number_of_variants": "0",
            "variants": {},
            "number_of_sightings": "17",
            "last_sighting": "2016-06-28 09:35:49",
            "number_of_citations": "0"
        }, {
            "vocabulary": "domes",
            "variant_of": {},
            "pronunciation": {},
            "meaning": "Hispanic word for a person from the Dominican Republic, possibly from the Washington Heights area of New York City.",
            "language": "eng",
            "about_ethnicity": "1",
            "about_nationality": "1",
            "about_religion": "0",
            "about_gender": "0",
            "about_sexual_orientation": "0",
            "about_disability": "0",
            "about_class": "0",
            "archaic": "0",
            "offensiveness": "0.00",
            "number_of_revisions": "0",
            "number_of_variants": "0",
            "variants": {},
            "number_of_sightings": "0",
            "last_sighting": {},
            "number_of_citations": "0"
        }, {
            "vocabulary": "dot head",
            "variant_of": {},
            "pronunciation": {},
            "meaning": "A person of Indian descent, from the caste-mark (dot) on an Indian's forehead.",
            "language": "eng",
            "about_ethnicity": "1",
            "about_nationality": "1",
            "about_religion": "0",
            "about_gender": "0",
            "about_sexual_orientation": "0",
            "about_disability": "0",
            "about_class": "0",
            "archaic": "0",
            "offensiveness": "0.00",
            "number_of_revisions": "0",
            "number_of_variants": "0",
            "variants": {},
            "number_of_sightings": "0",
            "last_sighting": {},
            "number_of_citations": "0"
        }, {
            "vocabulary": "dyke jumper",
            "variant_of": {},
            "pronunciation": {},
            "meaning": "A person of Dutch origin.",
            "language": "eng",
            "about_ethnicity": "0",
            "about_nationality": "1",
            "about_religion": "0",
            "about_gender": "0",
            "about_sexual_orientation": "0",
            "about_disability": "0",
            "about_class": "0",
            "archaic": "0",
            "offensiveness": "0.00",
            "number_of_revisions": "0",
            "number_of_variants": "0",
            "variants": {},
            "number_of_sightings": "2",
            "last_sighting": "2016-07-06 17:26:21",
            "number_of_citations": "0"
        }, {
            "vocabulary": "eh hole",
            "variant_of": {},
            "pronunciation": {},
            "meaning": "A Canadian. Variation on the ubiquitous 'eh' and the word 'asshole'.",
            "language": "eng",
            "about_ethnicity": "0",
            "about_nationality": "1",
            "about_religion": "0",
            "about_gender": "0",
            "about_sexual_orientation": "0",
            "about_disability": "0",
            "about_class": "0",
            "archaic": "0",
            "offensiveness": "0.00",
            "number_of_revisions": "0",
            "number_of_variants": "0",
            "variants": {},
            "number_of_sightings": "28",
            "last_sighting": "2016-07-26 17:18:17",
            "number_of_citations": "0"
        }, {
            "vocabulary": "eyetie",
            "variant_of": {},
            "pronunciation": {},
            "meaning": "An Italian person. Originated through the mispronunciation of 'Italian' as 'Eye-talian.'",
            "language": "eng",
            "about_ethnicity": "1",
            "about_nationality": "1",
            "about_religion": "0",
            "about_gender": "0",
            "about_sexual_orientation": "0",
            "about_disability": "0",
            "about_class": "0",
            "archaic": "0",
            "offensiveness": "0.86",
            "number_of_revisions": "0",
            "number_of_variants": "0",
            "variants": {},
            "number_of_sightings": "126",
            "last_sighting": "2016-09-17 15:47:25",
            "number_of_citations": "0"
        }, {
            "vocabulary": "FOB",
            "variant_of": "fresh off the boat",
            "pronunciation": {},
            "meaning": "A person of foreign nationality.",
            "language": "eng",
            "about_ethnicity": "0",
            "about_nationality": "1",
            "about_religion": "0",
            "about_gender": "0",
            "about_sexual_orientation": "0",
            "about_disability": "0",
            "about_class": "0",
            "archaic": "0",
            "offensiveness": "0.00",
            "number_of_revisions": "0",
            "number_of_variants": "0",
            "variants": {},
            "number_of_sightings": "0",
            "last_sighting": {},
            "number_of_citations": "0"
        }, {
            "vocabulary": "fog nigger",
            "variant_of": {},
            "pronunciation": {},
            "meaning": "A black person of British nationality.",
            "language": "eng",
            "about_ethnicity": "1",
            "about_nationality": "1",
            "about_religion": "0",
            "about_gender": "0",
            "about_sexual_orientation": "0",
            "about_disability": "0",
            "about_class": "0",
            "archaic": "0",
            "offensiveness": "0.00",
            "number_of_revisions": "0",
            "number_of_variants": "0",
            "variants": {},
            "number_of_sightings": "0",
            "last_sighting": {},
            "number_of_citations": "0"
        }, {
            "vocabulary": "fresh off the boat",
            "variant_of": {},
            "pronunciation": {},
            "meaning": "A person of foreign nationality.",
            "language": "eng",
            "about_ethnicity": "0",
            "about_nationality": "1",
            "about_religion": "0",
            "about_gender": "0",
            "about_sexual_orientation": "0",
            "about_disability": "0",
            "about_class": "0",
            "archaic": "0",
            "offensiveness": "0.00",
            "number_of_revisions": "0",
            "number_of_variants": "1",
            "variants": "FOB",
            "number_of_sightings": "2",
            "last_sighting": "2013-06-18 20:59:10",
            "number_of_citations": "0"
        }, {
            "vocabulary": "gew",
            "variant_of": {},
            "pronunciation": {},
            "meaning": "A German Jew.",
            "language": "eng",
            "about_ethnicity": "1",
            "about_nationality": "1",
            "about_religion": "1",
            "about_gender": "0",
            "about_sexual_orientation": "0",
            "about_disability": "0",
            "about_class": "0",
            "archaic": "0",
            "offensiveness": "0.00",
            "number_of_revisions": "0",
            "number_of_variants": "0",
            "variants": {},
            "number_of_sightings": "0",
            "last_sighting": {},
            "number_of_citations": "0"
        }, {
            "vocabulary": "ginzo",
            "variant_of": "guinea",
            "pronunciation": {},
            "meaning": "A person of Italian birth or descent. Most likely derived from 'Guinea Negro,' implying that Italians are dark or swarthy-skinned like the natives of Guinea. The diminutive 'Ginzo' probably dates back to World War II and is derived from Australian slang picked up by US servicemen in the Pacific Theater.",
            "language": "eng",
            "about_ethnicity": "1",
            "about_nationality": "1",
            "about_religion": "0",
            "about_gender": "0",
            "about_sexual_orientation": "0",
            "about_disability": "0",
            "about_class": "0",
            "archaic": "0",
            "offensiveness": "0.96",
            "number_of_revisions": "0",
            "number_of_variants": "0",
            "variants": {},
            "number_of_sightings": "73",
            "last_sighting": "2016-08-19 18:28:34",
            "number_of_citations": "0"
        }, {
            "vocabulary": "greaseball",
            "variant_of": {},
            "pronunciation": {},
            "meaning": "A person of Italian descent. It can also refer to any person of Mediterranean / Southern European descent or Hispanic descent.",
            "language": "eng",
            "about_ethnicity": "1",
            "about_nationality": "1",
            "about_religion": "0",
            "about_gender": "0",
            "about_sexual_orientation": "0",
            "about_disability": "0",
            "about_class": "0",
            "archaic": "0",
            "offensiveness": "0.94",
            "number_of_revisions": "0",
            "number_of_variants": "1",
            "variants": "greaser",
            "number_of_sightings": "3777",
            "last_sighting": "2016-10-02 13:32:28",
            "number_of_citations": "0"
        }, {
            "vocabulary": "greaser",
            "variant_of": "greaseball",
            "pronunciation": {},
            "meaning": "A person of Italian descent. It can also refer to any person of Mediterranean / Southern European descent or Hispanic descent.",
            "language": "eng",
            "about_ethnicity": "1",
            "about_nationality": "1",
            "about_religion": "0",
            "about_gender": "0",
            "about_sexual_orientation": "0",
            "about_disability": "0",
            "about_class": "0",
            "archaic": "0",
            "offensiveness": "0.86",
            "number_of_revisions": "0",
            "number_of_variants": "0",
            "variants": {},
            "number_of_sightings": "5",
            "last_sighting": "2013-07-31 05:43:40",
            "number_of_citations": "0"
        }, {
            "vocabulary": "guala",
            "variant_of": {},
            "pronunciation": {},
            "meaning": "A person who's overt about his/her Hispanic descent, particularly a Dominican",
            "language": "eng",
            "about_ethnicity": "1",
            "about_nationality": "1",
            "about_religion": "0",
            "about_gender": "0",
            "about_sexual_orientation": "0",
            "about_disability": "0",
            "about_class": "0",
            "archaic": "0",
            "offensiveness": "0.00",
            "number_of_revisions": "1",
            "number_of_variants": "1",
            "variants": "guala guala",
            "number_of_sightings": "1798",
            "last_sighting": "2016-09-27 01:57:17",
            "number_of_citations": "1"
        }, {
            "vocabulary": "guala guala",
            "variant_of": "guala",
            "pronunciation": {},
            "meaning": "A person who's overt about his/her Hispanic descent, particularly a Dominican",
            "language": "eng",
            "about_ethnicity": "1",
            "about_nationality": "1",
            "about_religion": "0",
            "about_gender": "0",
            "about_sexual_orientation": "0",
            "about_disability": "0",
            "about_class": "0",
            "archaic": "0",
            "offensiveness": "0.00",
            "number_of_revisions": "1",
            "number_of_variants": "0",
            "variants": {},
            "number_of_sightings": "30",
            "last_sighting": "2016-08-15 11:53:06",
            "number_of_citations": "0"
        }, {
            "vocabulary": "guido",
            "variant_of": {},
            "pronunciation": {},
            "meaning": "An Italian-American male. Derives from the Italian given name, Guido. Used mostly in the Northeastern United States as a stereotype for working-class urban Italian-Americans.",
            "language": "eng",
            "about_ethnicity": "1",
            "about_nationality": "1",
            "about_religion": "0",
            "about_gender": "0",
            "about_sexual_orientation": "0",
            "about_disability": "0",
            "about_class": "0",
            "archaic": "0",
            "offensiveness": "0.92",
            "number_of_revisions": "0",
            "number_of_variants": "0",
            "variants": {},
            "number_of_sightings": "23",
            "last_sighting": "2016-08-15 16:58:32",
            "number_of_citations": "0"
        }, {
            "vocabulary": "guinea",
            "variant_of": {},
            "pronunciation": {},
            "meaning": "A person of Italian birth or descent. Most likely derived from 'Guinea Negro,' implying that Italians are dark or swarthy-skinned like the natives of Guinea. The diminutive 'Ginzo' probably dates back to World War II and is derived from Australian slang picked up by US servicemen in the Pacific Theater.",
            "language": "eng",
            "about_ethnicity": "1",
            "about_nationality": "1",
            "about_religion": "0",
            "about_gender": "0",
            "about_sexual_orientation": "0",
            "about_disability": "0",
            "about_class": "0",
            "archaic": "0",
            "offensiveness": "1.00",
            "number_of_revisions": "0",
            "number_of_variants": "1",
            "variants": "ginzo",
            "number_of_sightings": "2",
            "last_sighting": "2013-06-22 15:07:51",
            "number_of_citations": "0"
        }, {
            "vocabulary": "Gwat",
            "variant_of": {},
            "pronunciation": {},
            "meaning": "Short for Guatemalan.",
            "language": "eng",
            "about_ethnicity": "0",
            "about_nationality": "1",
            "about_religion": "0",
            "about_gender": "0",
            "about_sexual_orientation": "0",
            "about_disability": "0",
            "about_class": "0",
            "archaic": "0",
            "offensiveness": "0.00",
            "number_of_revisions": "0",
            "number_of_variants": "0",
            "variants": {},
            "number_of_sightings": "60",
            "last_sighting": "2016-09-25 12:42:01",
            "number_of_citations": "0"
        }, {
            "vocabulary": "heinie",
            "variant_of": {},
            "pronunciation": {},
            "meaning": "A person of German descent.",
            "language": "eng",
            "about_ethnicity": "0",
            "about_nationality": "1",
            "about_religion": "0",
            "about_gender": "0",
            "about_sexual_orientation": "0",
            "about_disability": "0",
            "about_class": "0",
            "archaic": "0",
            "offensiveness": "0.00",
            "number_of_revisions": "0",
            "number_of_variants": "0",
            "variants": {},
            "number_of_sightings": "0",
            "last_sighting": {},
            "number_of_citations": "0"
        }, {
            "vocabulary": "Honyak",
            "variant_of": "Hunyak",
            "pronunciation": {},
            "meaning": "A Hungarian-Polish person.",
            "language": "eng",
            "about_ethnicity": "0",
            "about_nationality": "1",
            "about_religion": "0",
            "about_gender": "0",
            "about_sexual_orientation": "0",
            "about_disability": "0",
            "about_class": "0",
            "archaic": "0",
            "offensiveness": "0.00",
            "number_of_revisions": "0",
            "number_of_variants": "0",
            "variants": {},
            "number_of_sightings": "0",
            "last_sighting": {},
            "number_of_citations": "0"
        }, {
            "vocabulary": "Honyock",
            "variant_of": "Hunyak",
            "pronunciation": {},
            "meaning": "A Hungarian-Polish person.",
            "language": "eng",
            "about_ethnicity": "0",
            "about_nationality": "1",
            "about_religion": "0",
            "about_gender": "0",
            "about_sexual_orientation": "0",
            "about_disability": "0",
            "about_class": "0",
            "archaic": "0",
            "offensiveness": "0.00",
            "number_of_revisions": "0",
            "number_of_variants": "0",
            "variants": {},
            "number_of_sightings": "8",
            "last_sighting": "2016-07-26 10:35:07",
            "number_of_citations": "0"
        }, {
            "vocabulary": "hoser",
            "variant_of": {},
            "pronunciation": {},
            "meaning": "In Canada, an unsophisticated person, Back when Hockey was played on frozen ponds and lakes the losers of the hockey game would have to hose the lakes to become clean, smooth ice.  Calling someone a hoser is really just calling them a loser.  From the practice of stealing gas with a hose and siphon.",
            "language": "eng",
            "about_ethnicity": "0",
            "about_nationality": "1",
            "about_religion": "0",
            "about_gender": "0",
            "about_sexual_orientation": "0",
            "about_disability": "0",
            "about_class": "1",
            "archaic": "0",
            "offensiveness": "0.10",
            "number_of_revisions": "1",
            "number_of_variants": "0",
            "variants": {},
            "number_of_sightings": "2762",
            "last_sighting": "2016-10-02 03:10:32",
            "number_of_citations": "1"
        }, {
            "vocabulary": "Hun",
            "variant_of": {},
            "pronunciation": {},
            "meaning": "[1] A German, especially a German soldier; popular during World War I. Derived from a speech given by Kaiser Wilhelm of Germany to the German contingent sent to China during the Boxer Rebellion in which he exhorted them to 'be like Huns' (i.e., savage and ruthless) to their Chinese enemy. [2] A Protestant in Northern Ireland. [3] A member of the British military in Ireland ('Britannia's huns').",
            "language": "eng",
            "about_ethnicity": "0",
            "about_nationality": "1",
            "about_religion": "1",
            "about_gender": "0",
            "about_sexual_orientation": "0",
            "about_disability": "0",
            "about_class": "0",
            "archaic": "1",
            "offensiveness": "0.00",
            "number_of_revisions": "0",
            "number_of_variants": "0",
            "variants": {},
            "number_of_sightings": "169",
            "last_sighting": "2016-09-26 19:58:26",
            "number_of_citations": "0"
        }, {
            "vocabulary": "Hunkie",
            "variant_of": "Hunky",
            "pronunciation": {},
            "meaning": "[1] A Hungarian. [2] A person of central or east European birth or descent.",
            "language": "eng",
            "about_ethnicity": "1",
            "about_nationality": "1",
            "about_religion": "0",
            "about_gender": "0",
            "about_sexual_orientation": "0",
            "about_disability": "0",
            "about_class": "0",
            "archaic": "0",
            "offensiveness": "0.00",
            "number_of_revisions": "0",
            "number_of_variants": "0",
            "variants": {},
            "number_of_sightings": "0",
            "last_sighting": {},
            "number_of_citations": "0"
        }, {
            "vocabulary": "Hunky",
            "variant_of": {},
            "pronunciation": {},
            "meaning": "[1] A Hungarian. [2] A person of central or east European birth or descent.",
            "language": "eng",
            "about_ethnicity": "1",
            "about_nationality": "1",
            "about_religion": "0",
            "about_gender": "0",
            "about_sexual_orientation": "0",
            "about_disability": "0",
            "about_class": "0",
            "archaic": "0",
            "offensiveness": "0.00",
            "number_of_revisions": "0",
            "number_of_variants": "1",
            "variants": "Hunkie",
            "number_of_sightings": "0",
            "last_sighting": {},
            "number_of_citations": "0"
        }, {
            "vocabulary": "Hunyak",
            "variant_of": {},
            "pronunciation": {},
            "meaning": "A Hungarian-Polish person.",
            "language": "eng",
            "about_ethnicity": "0",
            "about_nationality": "1",
            "about_religion": "0",
            "about_gender": "0",
            "about_sexual_orientation": "0",
            "about_disability": "0",
            "about_class": "0",
            "archaic": "0",
            "offensiveness": "0.00",
            "number_of_revisions": "0",
            "number_of_variants": "3",
            "variants": "Honyak; Honyock; Hunyock",
            "number_of_sightings": "11",
            "last_sighting": "2016-09-10 14:32:13",
            "number_of_citations": "0"
        }, {
            "vocabulary": "Hunyock",
            "variant_of": "Hunyak",
            "pronunciation": {},
            "meaning": "A Hungarian-Polish person.",
            "language": "eng",
            "about_ethnicity": "0",
            "about_nationality": "1",
            "about_religion": "0",
            "about_gender": "0",
            "about_sexual_orientation": "0",
            "about_disability": "0",
            "about_class": "0",
            "archaic": "0",
            "offensiveness": "0.00",
            "number_of_revisions": "0",
            "number_of_variants": "0",
            "variants": {},
            "number_of_sightings": "2",
            "last_sighting": "2016-07-23 14:29:26",
            "number_of_citations": "0"
        }, {
            "vocabulary": "ice monkey",
            "variant_of": {},
            "pronunciation": {},
            "meaning": "A Finn.",
            "language": "eng",
            "about_ethnicity": "0",
            "about_nationality": "1",
            "about_religion": "0",
            "about_gender": "0",
            "about_sexual_orientation": "0",
            "about_disability": "0",
            "about_class": "0",
            "archaic": "0",
            "offensiveness": "0.00",
            "number_of_revisions": "0",
            "number_of_variants": "0",
            "variants": {},
            "number_of_sightings": "6",
            "last_sighting": "2016-08-02 15:04:28",
            "number_of_citations": "0"
        }, {
            "vocabulary": "ice nigger",
            "variant_of": {},
            "pronunciation": {},
            "meaning": "A black Canadian.",
            "language": "eng",
            "about_ethnicity": "1",
            "about_nationality": "1",
            "about_religion": "0",
            "about_gender": "0",
            "about_sexual_orientation": "0",
            "about_disability": "0",
            "about_class": "0",
            "archaic": "0",
            "offensiveness": "0.21",
            "number_of_revisions": "0",
            "number_of_variants": "0",
            "variants": {},
            "number_of_sightings": "44",
            "last_sighting": "2016-07-15 23:36:41",
            "number_of_citations": "0"
        }, {
            "vocabulary": "island nigger",
            "variant_of": {},
            "pronunciation": {},
            "meaning": "A Polynesian.",
            "language": "eng",
            "about_ethnicity": "1",
            "about_nationality": "1",
            "about_religion": "0",
            "about_gender": "0",
            "about_sexual_orientation": "0",
            "about_disability": "0",
            "about_class": "0",
            "archaic": "0",
            "offensiveness": "0.00",
            "number_of_revisions": "0",
            "number_of_variants": "0",
            "variants": {},
            "number_of_sightings": "52",
            "last_sighting": "2016-08-12 11:57:36",
            "number_of_citations": "0"
        }, {
            "vocabulary": "Jap",
            "variant_of": {},
            "pronunciation": {},
            "meaning": "[1] A Japanese soldier or national, or anyone of Japanese descent. [2] Acronym for 'Jewish-American Princess.'",
            "language": "eng",
            "about_ethnicity": "1",
            "about_nationality": "1",
            "about_religion": "0",
            "about_gender": "0",
            "about_sexual_orientation": "0",
            "about_disability": "0",
            "about_class": "0",
            "archaic": "0",
            "offensiveness": "0.00",
            "number_of_revisions": "0",
            "number_of_variants": "1",
            "variants": "Whipped",
            "number_of_sightings": "254",
            "last_sighting": "2016-10-02 01:14:43",
            "number_of_citations": "0"
        }, {
            "vocabulary": "japie",
            "variant_of": {},
            "pronunciation": {},
            "meaning": "Derogatory term for a Caucasian South African, possibly derived from the Dutch term 'plaasjapie' meaning a farm-boy",
            "language": "eng",
            "about_ethnicity": "1",
            "about_nationality": "1",
            "about_religion": "0",
            "about_gender": "0",
            "about_sexual_orientation": "0",
            "about_disability": "0",
            "about_class": "0",
            "archaic": "0",
            "offensiveness": "0.00",
            "number_of_revisions": "1",
            "number_of_variants": "0",
            "variants": {},
            "number_of_sightings": "58",
            "last_sighting": "2016-09-28 15:21:03",
            "number_of_citations": "0"
        }, {
            "vocabulary": "Jerry",
            "variant_of": {},
            "pronunciation": {},
            "meaning": "A German, especially a German soldier (probably an alteration of German). Origin of Jerry can.",
            "language": "eng",
            "about_ethnicity": "0",
            "about_nationality": "1",
            "about_religion": "0",
            "about_gender": "0",
            "about_sexual_orientation": "0",
            "about_disability": "0",
            "about_class": "0",
            "archaic": "0",
            "offensiveness": "0.00",
            "number_of_revisions": "0",
            "number_of_variants": "0",
            "variants": {},
            "number_of_sightings": "0",
            "last_sighting": {},
            "number_of_citations": "0"
        }, {
            "vocabulary": "knacker",
            "variant_of": {},
            "pronunciation": {},
            "meaning": "An Irish Traveller.",
            "language": "eng",
            "about_ethnicity": "1",
            "about_nationality": "1",
            "about_religion": "0",
            "about_gender": "0",
            "about_sexual_orientation": "0",
            "about_disability": "0",
            "about_class": "0",
            "archaic": "0",
            "offensiveness": "0.33",
            "number_of_revisions": "0",
            "number_of_variants": "0",
            "variants": {},
            "number_of_sightings": "4685",
            "last_sighting": "2016-10-06 18:47:16",
            "number_of_citations": "0"
        }, {
            "vocabulary": "kraut",
            "variant_of": {},
            "pronunciation": {},
            "meaning": "A German, most specifically during World War II. From Sauerkraut.",
            "language": "eng",
            "about_ethnicity": "0",
            "about_nationality": "1",
            "about_religion": "0",
            "about_gender": "0",
            "about_sexual_orientation": "0",
            "about_disability": "0",
            "about_class": "0",
            "archaic": "1",
            "offensiveness": "0.00",
            "number_of_revisions": "0",
            "number_of_variants": "0",
            "variants": {},
            "number_of_sightings": "265",
            "last_sighting": "2016-10-06 21:21:44",
            "number_of_citations": "0"
        }, {
            "vocabulary": "Leb",
            "variant_of": {},
            "pronunciation": {},
            "meaning": "A person of Lebanese descent.",
            "language": "eng",
            "about_ethnicity": "0",
            "about_nationality": "1",
            "about_religion": "0",
            "about_gender": "0",
            "about_sexual_orientation": "0",
            "about_disability": "0",
            "about_class": "0",
            "archaic": "0",
            "offensiveness": "0.00",
            "number_of_revisions": "0",
            "number_of_variants": "1",
            "variants": "Lebbo",
            "number_of_sightings": "62",
            "last_sighting": "2016-10-01 08:28:53",
            "number_of_citations": "0"
        }, {
            "vocabulary": "Lebbo",
            "variant_of": "Leb",
            "pronunciation": {},
            "meaning": "A person of Lebanese descent.",
            "language": "eng",
            "about_ethnicity": "0",
            "about_nationality": "1",
            "about_religion": "0",
            "about_gender": "0",
            "about_sexual_orientation": "0",
            "about_disability": "0",
            "about_class": "0",
            "archaic": "0",
            "offensiveness": "0.00",
            "number_of_revisions": "0",
            "number_of_variants": "0",
            "variants": {},
            "number_of_sightings": "69",
            "last_sighting": "2016-09-24 22:28:39",
            "number_of_citations": "0"
        }, {
            "vocabulary": "leprechaun",
            "variant_of": {},
            "pronunciation": {},
            "meaning": "A person of Irish descent.",
            "language": "eng",
            "about_ethnicity": "0",
            "about_nationality": "1",
            "about_religion": "0",
            "about_gender": "0",
            "about_sexual_orientation": "0",
            "about_disability": "0",
            "about_class": "0",
            "archaic": "0",
            "offensiveness": "0.00",
            "number_of_revisions": "0",
            "number_of_variants": "0",
            "variants": {},
            "number_of_sightings": "1",
            "last_sighting": "2013-04-28 03:43:05",
            "number_of_citations": "0"
        }, {
            "vocabulary": "limey",
            "variant_of": {},
            "pronunciation": {},
            "meaning": "A British person. Comes from the historical British naval practice of giving sailors limes to stave off scurvy.",
            "language": "eng",
            "about_ethnicity": "0",
            "about_nationality": "1",
            "about_religion": "0",
            "about_gender": "0",
            "about_sexual_orientation": "0",
            "about_disability": "0",
            "about_class": "0",
            "archaic": "0",
            "offensiveness": "0.27",
            "number_of_revisions": "0",
            "number_of_variants": "0",
            "variants": {},
            "number_of_sightings": "1561",
            "last_sighting": "2016-10-06 16:20:04",
            "number_of_citations": "0"
        }, {
            "vocabulary": "lowlander",
            "variant_of": {},
            "pronunciation": {},
            "meaning": "A person in the Netherlands, which is 20% below sea level.",
            "language": "eng",
            "about_ethnicity": "0",
            "about_nationality": "1",
            "about_religion": "0",
            "about_gender": "0",
            "about_sexual_orientation": "0",
            "about_disability": "0",
            "about_class": "0",
            "archaic": "0",
            "offensiveness": "0.00",
            "number_of_revisions": "0",
            "number_of_variants": "0",
            "variants": {},
            "number_of_sightings": "35",
            "last_sighting": "2016-09-23 07:43:15",
            "number_of_citations": "0"
        }, {
            "vocabulary": "lugan",
            "variant_of": {},
            "pronunciation": {},
            "meaning": "A Lithuanian, particularly a Lithuanian American.",
            "language": "eng",
            "about_ethnicity": "0",
            "about_nationality": "1",
            "about_religion": "0",
            "about_gender": "0",
            "about_sexual_orientation": "0",
            "about_disability": "0",
            "about_class": "0",
            "archaic": "0",
            "offensiveness": "0.00",
            "number_of_revisions": "0",
            "number_of_variants": "0",
            "variants": {},
            "number_of_sightings": "52",
            "last_sighting": "2016-09-30 10:35:26",
            "number_of_citations": "0"
        }, {
            "vocabulary": "mack",
            "variant_of": "mick",
            "pronunciation": {},
            "meaning": "[1] An Irish person or a person of Irish descent. Mick is considered more offensive in the UK and US. From the prefix 'Mc'/'Mac' meaning 'son of' that is commonly found in Irish surnames. [2] In Australia, used to denote a Roman Catholic [19th century on, from Micheal].",
            "language": "eng",
            "about_ethnicity": "1",
            "about_nationality": "1",
            "about_religion": "0",
            "about_gender": "0",
            "about_sexual_orientation": "0",
            "about_disability": "0",
            "about_class": "0",
            "archaic": "0",
            "offensiveness": "0.00",
            "number_of_revisions": "1",
            "number_of_variants": "0",
            "variants": {},
            "number_of_sightings": "0",
            "last_sighting": {},
            "number_of_citations": "0"
        }, {
            "vocabulary": "Merkin",
            "variant_of": {},
            "pronunciation": {},
            "meaning": "Similar to 'American.'",
            "language": "eng",
            "about_ethnicity": "0",
            "about_nationality": "1",
            "about_religion": "0",
            "about_gender": "0",
            "about_sexual_orientation": "0",
            "about_disability": "0",
            "about_class": "0",
            "archaic": "0",
            "offensiveness": "0.00",
            "number_of_revisions": "0",
            "number_of_variants": "0",
            "variants": {},
            "number_of_sightings": "0",
            "last_sighting": {},
            "number_of_citations": "0"
        }, {
            "vocabulary": "mick",
            "variant_of": {},
            "pronunciation": "mk",
            "meaning": "[1] An Irish person or a person of Irish descent. Mick is considered more offensive in the UK and US. From the prefix 'Mc'/'Mac' meaning 'son of' that is commonly found in Irish surnames. [2] In Australia, used to denote a Roman Catholic [19th century on, from Micheal].",
            "language": "eng",
            "about_ethnicity": "1",
            "about_nationality": "1",
            "about_religion": "0",
            "about_gender": "0",
            "about_sexual_orientation": "0",
            "about_disability": "0",
            "about_class": "0",
            "archaic": "0",
            "offensiveness": "0.70",
            "number_of_revisions": "1",
            "number_of_variants": "3",
            "variants": "mack; mickey; Mickey Finn",
            "number_of_sightings": "79",
            "last_sighting": "2016-09-23 00:39:18",
            "number_of_citations": "0"
        }, {
            "vocabulary": "mickey",
            "variant_of": "mick",
            "pronunciation": {},
            "meaning": "[1] An Irish person or a person of Irish descent. Mick is considered more offensive in the UK and US. From the prefix 'Mc'/'Mac' meaning 'son of' that is commonly found in Irish surnames. [2] In Australia, used to denote a Roman Catholic [19th century on, from Micheal].",
            "language": "eng",
            "about_ethnicity": "1",
            "about_nationality": "1",
            "about_religion": "0",
            "about_gender": "0",
            "about_sexual_orientation": "0",
            "about_disability": "0",
            "about_class": "0",
            "archaic": "0",
            "offensiveness": "0.00",
            "number_of_revisions": "1",
            "number_of_variants": "0",
            "variants": {},
            "number_of_sightings": "0",
            "last_sighting": {},
            "number_of_citations": "0"
        }, {
            "vocabulary": "Mickey Finn",
            "variant_of": "mick",
            "pronunciation": {},
            "meaning": "[1] An Irish person or a person of Irish descent. Mick is considered more offensive in the UK and US. From the prefix 'Mc'/'Mac' meaning 'son of' that is commonly found in Irish surnames. [2] In Australia, used to denote a Roman Catholic [19th century on, from Micheal].",
            "language": "eng",
            "about_ethnicity": "1",
            "about_nationality": "1",
            "about_religion": "0",
            "about_gender": "0",
            "about_sexual_orientation": "0",
            "about_disability": "0",
            "about_class": "0",
            "archaic": "0",
            "offensiveness": "0.00",
            "number_of_revisions": "1",
            "number_of_variants": "0",
            "variants": {},
            "number_of_sightings": "0",
            "last_sighting": {},
            "number_of_citations": "0"
        }, {
            "vocabulary": "mung",
            "variant_of": {},
            "pronunciation": {},
            "meaning": "Pronunciation of 'hmong', the Vietnamese people which were relocated to the United States during and after the Vietnam War.",
            "language": "eng",
            "about_ethnicity": "1",
            "about_nationality": "1",
            "about_religion": "0",
            "about_gender": "0",
            "about_sexual_orientation": "0",
            "about_disability": "0",
            "about_class": "0",
            "archaic": "0",
            "offensiveness": "0.00",
            "number_of_revisions": "0",
            "number_of_variants": "0",
            "variants": {},
            "number_of_sightings": "0",
            "last_sighting": {},
            "number_of_citations": "0"
        }, {
            "vocabulary": "nip",
            "variant_of": {},
            "pronunciation": {},
            "meaning": "A person of Japanese descent (shortened version of Nipponese, from Japanese name for Japan, Nippon).",
            "language": "eng",
            "about_ethnicity": "0",
            "about_nationality": "1",
            "about_religion": "0",
            "about_gender": "0",
            "about_sexual_orientation": "0",
            "about_disability": "0",
            "about_class": "0",
            "archaic": "0",
            "offensiveness": "0.00",
            "number_of_revisions": "0",
            "number_of_variants": "0",
            "variants": {},
            "number_of_sightings": "0",
            "last_sighting": {},
            "number_of_citations": "0"
        }, {
            "vocabulary": "ocker",
            "variant_of": {},
            "pronunciation": {},
            "meaning": "An uncultivated Australian.",
            "language": "eng",
            "about_ethnicity": "0",
            "about_nationality": "1",
            "about_religion": "0",
            "about_gender": "0",
            "about_sexual_orientation": "0",
            "about_disability": "0",
            "about_class": "0",
            "archaic": "0",
            "offensiveness": "0.00",
            "number_of_revisions": "0",
            "number_of_variants": "0",
            "variants": {},
            "number_of_sightings": "473",
            "last_sighting": "2016-10-05 06:12:40",
            "number_of_citations": "0"
        }, {
            "vocabulary": "paddy",
            "variant_of": {},
            "pronunciation": {},
            "meaning": "A person of Irish descent, derived from a nickname for Padraig.",
            "language": "eng",
            "about_ethnicity": "1",
            "about_nationality": "1",
            "about_religion": "0",
            "about_gender": "0",
            "about_sexual_orientation": "0",
            "about_disability": "0",
            "about_class": "0",
            "archaic": "0",
            "offensiveness": "0.00",
            "number_of_revisions": "1",
            "number_of_variants": "0",
            "variants": {},
            "number_of_sightings": "185",
            "last_sighting": "2016-09-29 19:18:13",
            "number_of_citations": "0"
        }, {
            "vocabulary": "paki",
            "variant_of": {},
            "pronunciation": {},
            "meaning": "A person from South Asia or the Middle East, particularly a person from Pakistan.",
            "language": "eng",
            "about_ethnicity": "1",
            "about_nationality": "1",
            "about_religion": "0",
            "about_gender": "0",
            "about_sexual_orientation": "0",
            "about_disability": "0",
            "about_class": "0",
            "archaic": "0",
            "offensiveness": "0.90",
            "number_of_revisions": "0",
            "number_of_variants": "0",
            "variants": {},
            "number_of_sightings": "376",
            "last_sighting": "2016-10-05 06:03:48",
            "number_of_citations": "0"
        }, {
            "vocabulary": "Pepper",
            "variant_of": {},
            "pronunciation": {},
            "meaning": "A French Canadian or Quebecois, derived from the Anglo-Canadian jibe that their stereotypically bad dental hygiene was due to drinking Pepsi or Dr Pepper for breakfast.",
            "language": "eng",
            "about_ethnicity": "1",
            "about_nationality": "1",
            "about_religion": "0",
            "about_gender": "0",
            "about_sexual_orientation": "0",
            "about_disability": "0",
            "about_class": "0",
            "archaic": "0",
            "offensiveness": "0.00",
            "number_of_revisions": "0",
            "number_of_variants": "1",
            "variants": "Pepsi",
            "number_of_sightings": "0",
            "last_sighting": {},
            "number_of_citations": "0"
        }, {
            "vocabulary": "Pepsi",
            "variant_of": "Pepper",
            "pronunciation": {},
            "meaning": "A French Canadian or Quebecois, derived from the Anglo-Canadian jibe that their stereotypically bad dental hygiene was due to drinking Pepsi or Dr Pepper for breakfast.",
            "language": "eng",
            "about_ethnicity": "1",
            "about_nationality": "1",
            "about_religion": "0",
            "about_gender": "0",
            "about_sexual_orientation": "0",
            "about_disability": "0",
            "about_class": "0",
            "archaic": "0",
            "offensiveness": "0.00",
            "number_of_revisions": "0",
            "number_of_variants": "0",
            "variants": {},
            "number_of_sightings": "0",
            "last_sighting": {},
            "number_of_citations": "0"
        }, {
            "vocabulary": "piker",
            "variant_of": "pikey",
            "pronunciation": {},
            "meaning": "Derived from 'turnpike'. [1] An Irish person. [2] A gypsy. [3] An itinerant or vagrant lower-class or poor person.",
            "language": "eng",
            "about_ethnicity": "1",
            "about_nationality": "1",
            "about_religion": "0",
            "about_gender": "0",
            "about_sexual_orientation": "0",
            "about_disability": "0",
            "about_class": "0",
            "archaic": "0",
            "offensiveness": "0.00",
            "number_of_revisions": "0",
            "number_of_variants": "0",
            "variants": {},
            "number_of_sightings": "412",
            "last_sighting": "2016-10-05 00:21:56",
            "number_of_citations": "0"
        }, {
            "vocabulary": "pikey",
            "variant_of": {},
            "pronunciation": {},
            "meaning": "Derived from 'turnpike'. [1] An Irish person. [2] A gypsy. [3] An itinerant or vagrant lower-class or poor person.",
            "language": "eng",
            "about_ethnicity": "1",
            "about_nationality": "1",
            "about_religion": "0",
            "about_gender": "0",
            "about_sexual_orientation": "0",
            "about_disability": "0",
            "about_class": "0",
            "archaic": "0",
            "offensiveness": "0.03",
            "number_of_revisions": "0",
            "number_of_variants": "2",
            "variants": "piky; piker",
            "number_of_sightings": "3311",
            "last_sighting": "2016-10-05 02:45:13",
            "number_of_citations": "0"
        }, {
            "vocabulary": "piky",
            "variant_of": "pikey",
            "pronunciation": {},
            "meaning": "Derived from 'turnpike'. [1] An Irish person. [2] A gypsy. [3] An itinerant or vagrant lower-class or poor person.",
            "language": "eng",
            "about_ethnicity": "1",
            "about_nationality": "1",
            "about_religion": "0",
            "about_gender": "0",
            "about_sexual_orientation": "0",
            "about_disability": "0",
            "about_class": "0",
            "archaic": "0",
            "offensiveness": "0.00",
            "number_of_revisions": "0",
            "number_of_variants": "0",
            "variants": {},
            "number_of_sightings": "0",
            "last_sighting": {},
            "number_of_citations": "0"
        }, {
            "vocabulary": "plastic paddy",
            "variant_of": {},
            "pronunciation": {},
            "meaning": "A non-Irish person who claims to be Irish.",
            "language": "eng",
            "about_ethnicity": "1",
            "about_nationality": "1",
            "about_religion": "0",
            "about_gender": "0",
            "about_sexual_orientation": "0",
            "about_disability": "0",
            "about_class": "0",
            "archaic": "0",
            "offensiveness": "0.33",
            "number_of_revisions": "1",
            "number_of_variants": "0",
            "variants": {},
            "number_of_sightings": "1834",
            "last_sighting": "2016-10-03 15:34:51",
            "number_of_citations": "0"
        }, {
            "vocabulary": "pogue",
            "variant_of": {},
            "pronunciation": {},
            "meaning": "A person of Irish descent.",
            "language": "eng",
            "about_ethnicity": "1",
            "about_nationality": "1",
            "about_religion": "0",
            "about_gender": "0",
            "about_sexual_orientation": "0",
            "about_disability": "0",
            "about_class": "0",
            "archaic": "0",
            "offensiveness": "0.00",
            "number_of_revisions": "0",
            "number_of_variants": "0",
            "variants": {},
            "number_of_sightings": "43",
            "last_sighting": "2016-09-18 00:50:00",
            "number_of_citations": "0"
        }, {
            "vocabulary": "pohm",
            "variant_of": "pom",
            "pronunciation": {},
            "meaning": "A British (usually English) immigrant. Some claim it derives from 'Prisoner of Mother England' or 'Prisoner of Her Majesty', but it probably derives from pomegranate, rhyming slang for 'immigrant'. It is often used irreverently and is usually considered offensive. Many such migrants to Australia, such as Prime Minister Julia Gillard, call themselves 'ten pound poms', because they paid ten pounds for their passage to Australia between 1945 and 1972 under an assisted migration scheme. Often combined with an adjective, particularly whingeing pom, a reference to migrants who complained about their adopted country. Often used in a sporting (especially cricket and rugby) context, with liberal use of 'pom' and 'Aussie' being used by the media; the term is often seen as unoffensive in this context, and instead as light-hearted banter by those who use it, but still possibly as offensive by those whom it is directed at.",
            "language": "eng",
            "about_ethnicity": "0",
            "about_nationality": "1",
            "about_religion": "0",
            "about_gender": "0",
            "about_sexual_orientation": "0",
            "about_disability": "0",
            "about_class": "0",
            "archaic": "0",
            "offensiveness": "0.00",
            "number_of_revisions": "0",
            "number_of_variants": "0",
            "variants": {},
            "number_of_sightings": "10",
            "last_sighting": "2015-12-25 00:24:08",
            "number_of_citations": "0"
        }]
    }
}
